flask_monocrud/AdminModel.py
flask_monocrud/QueryHandler.py
flask_monocrud/__init__.py
flask_monocrud/ext.py
flask_monocrud/flask_monocrud.py
flask_monocrud/action_components/__init__.py
flask_monocrud/flask_debugtoolbar/__init__.py
flask_monocrud/flask_debugtoolbar/compat.py
flask_monocrud/flask_debugtoolbar/toolbar.py
flask_monocrud/flask_debugtoolbar/utils.py
flask_monocrud/flask_debugtoolbar/panels/__init__.py
flask_monocrud/flask_debugtoolbar/panels/config_vars.py
flask_monocrud/flask_debugtoolbar/panels/g.py
flask_monocrud/flask_debugtoolbar/panels/headers.py
flask_monocrud/flask_debugtoolbar/panels/logger.py
flask_monocrud/flask_debugtoolbar/panels/profiler.py
flask_monocrud/flask_debugtoolbar/panels/request_vars.py
flask_monocrud/flask_debugtoolbar/panels/route_list.py
flask_monocrud/flask_debugtoolbar/panels/sqlalchemy.py
flask_monocrud/flask_debugtoolbar/panels/template.py
flask_monocrud/flask_debugtoolbar/panels/timer.py
flask_monocrud/flask_debugtoolbar/panels/versions.py
flask_monocrud/flask_debugtoolbar/static/codemirror/codemirror.css
flask_monocrud/flask_debugtoolbar/static/codemirror/codemirror.js
flask_monocrud/flask_debugtoolbar/static/codemirror/mode/clike/clike.js
flask_monocrud/flask_debugtoolbar/static/codemirror/mode/clike/index.html
flask_monocrud/flask_debugtoolbar/static/codemirror/mode/clojure/clojure.js
flask_monocrud/flask_debugtoolbar/static/codemirror/mode/clojure/index.html
flask_monocrud/flask_debugtoolbar/static/codemirror/mode/coffeescript/LICENSE
flask_monocrud/flask_debugtoolbar/static/codemirror/mode/coffeescript/coffeescript.js
flask_monocrud/flask_debugtoolbar/static/codemirror/mode/coffeescript/index.html
flask_monocrud/flask_debugtoolbar/static/codemirror/mode/css/css.js
flask_monocrud/flask_debugtoolbar/static/codemirror/mode/css/index.html
flask_monocrud/flask_debugtoolbar/static/codemirror/mode/diff/diff.css
flask_monocrud/flask_debugtoolbar/static/codemirror/mode/diff/diff.js
flask_monocrud-0.0.1rc36.dist-info/METADATA
flask_monocrud-0.0.1rc36.dist-info/WHEEL
flask_monocrud-0.0.1rc36.dist-info/top_level.txt
flask_monocrud-0.0.1rc36.dist-info/RECORD
