Metadata-Version: 2.1
Name: flask-monocrud
Version: 0.0.1rc36
Summary: Package provides utilities for managing fixture data python applications. It offers a convenient way to populate database tables with predefined data.
Home-page: https://github.com/JarriqTheTechie/flask-monocrud
Author: Jarriq Rolle
Author-email: jrolle@bnbbahamas.com
Classifier: Programming Language :: Python :: 3
Classifier: License :: OSI Approved :: MIT License
Classifier: Operating System :: OS Independent
Requires-Python: >=3.9
Requires-Dist: flask
Requires-Dist: flask-orphus
Requires-Dist: flask-wtf
Requires-Dist: masonite-orm
Requires-Dist: pyyaml
Requires-Dist: orjson
Requires-Dist: ward
Requires-Dist: currencies
Requires-Dist: packaging
